pipwrapper/__init__.py
pipwrapper/pipwrapper.py
pipwrapper-0.5.0.dist-info/LICENSE
pipwrapper-0.5.0.dist-info/METADATA
pipwrapper-0.5.0.dist-info/WHEEL
pipwrapper-0.5.0.dist-info/top_level.txt
pipwrapper-0.5.0.dist-info/RECORD
