Metadata-Version: 2.1
Name: pipwrapper
Version: 0.5.0
Summary: A simple, dependency-free library for using PIP via wrapping the CLI utility
Home-page: https://github.com/Privex/pipwrapper
Author: Chris (Someguy123) @ Privex
Author-email: chris@privex.io
License: MIT
Platform: UNKNOWN
Classifier: Programming Language :: Python :: 3
Classifier: Programming Language :: Python :: 3.6
Classifier: Programming Language :: Python :: 3.7
Classifier: Programming Language :: Python :: 3.8
Classifier: Programming Language :: Python :: 3.9
Classifier: License :: OSI Approved :: MIT License
Classifier: Operating System :: OS Independent
